server/__init__.py
server/server.old.py
server/server.py
markob-0.0.3.dist-info/METADATA
markob-0.0.3.dist-info/WHEEL
markob-0.0.3.dist-info/entry_points.txt
markob-0.0.3.dist-info/licenses/LICENSE.md
markob-0.0.3.dist-info/RECORD
