Metadata-Version: 2.1
Name: Markob
Version: 0.0.3
Summary: Markob API lets you highlight text on web pages and save it to Obsidian.
Project-URL: homepage, https://github.com/rooyca/markob
Project-URL: issues, https://github.com/rooyca/markob/issues
Author-email: rooyca <rooyca@gmail.com>
License: MIT
License-File: LICENSE.md
Classifier: License :: OSI Approved :: MIT License
Classifier: Operating System :: OS Independent
Classifier: Programming Language :: Python :: 3
Requires-Python: >=3.7
